transformer_embedder/__init__.py
transformer_embedder/embedder.py
transformer_embedder/tokenizer.py
transformer_embedder/utils.py
transformer_embedder-1.7.16.dist-info/METADATA
transformer_embedder-1.7.16.dist-info/WHEEL
transformer_embedder-1.7.16.dist-info/top_level.txt
transformer_embedder-1.7.16.dist-info/RECORD
