Metadata-Version: 2.1
Name: transformer-embedder
Version: 1.7.16
Summary: Word level transformer based embeddings
Home-page: https://github.com/Riccorl/transformer-embedder
Author: Riccardo Orlando
Author-email: orlandoricc@gmail.com
License: Apache
Keywords: NLP deep learning transformer pytorch BERT google subtoken wordpieces embeddings
Platform: UNKNOWN
Classifier: Programming Language :: Python :: 3
Classifier: License :: OSI Approved :: Apache Software License
Classifier: Operating System :: OS Independent
Requires-Python: >=3.6
Requires-Dist: transformers (<4.12,>=4.3)
Provides-Extra: all
Requires-Dist: torch (<1.10,>=1.5) ; extra == 'all'
Requires-Dist: spacy (<3.2,>=3.0) ; extra == 'all'
Provides-Extra: spacy
Requires-Dist: spacy (<3.2,>=3.0) ; extra == 'spacy'
Provides-Extra: torch
Requires-Dist: torch (<1.10,>=1.5) ; extra == 'torch'
